capm_metric/__init__.py
capm_metric/capm.py
tests/__init__.py
tests/test_core.py
capm_metrics-0.1.1.dist-info/METADATA
capm_metrics-0.1.1.dist-info/WHEEL
capm_metrics-0.1.1.dist-info/top_level.txt
capm_metrics-0.1.1.dist-info/RECORD
