Metadata-Version: 2.4
Name: capm-metrics
Version: 0.1.1
Summary: A stock performance tool based on the CAPM model
Home-page: https://github.com/C-Shi/capm_metrics
Author: Cheng Shi
Author-email: mr.cheng.shi@gmail.com
License: MIT
Project-URL: Bug Tracker, https://github.com/C-Shi/capm_metrics/issues
Project-URL: Documentation, https://github.com/C-Shi/capm_metrics#readme
Keywords: CAPM stock analysis finance
Classifier: Programming Language :: Python :: 3
Classifier: License :: OSI Approved :: MIT License
Classifier: Operating System :: OS Independent
Requires-Python: >=3.9
Requires-Dist: numpy>=2.0.2
Requires-Dist: pandas>=2.2.3
Requires-Dist: yfinance>=0.2.46
Provides-Extra: dev
Requires-Dist: pytest; extra == "dev"
Requires-Dist: pylint; extra == "dev"
Requires-Dist: pytest-cov; extra == "dev"
Dynamic: author
Dynamic: author-email
Dynamic: classifier
Dynamic: description
Dynamic: description-content-type
Dynamic: home-page
Dynamic: keywords
Dynamic: license
Dynamic: project-url
Dynamic: provides-extra
Dynamic: requires-dist
Dynamic: requires-python
Dynamic: summary
